trollspeak/__init__.py
trollspeak/troll.py
trollspeak-1.0.dist-info/LICENSE
trollspeak-1.0.dist-info/METADATA
trollspeak-1.0.dist-info/WHEEL
trollspeak-1.0.dist-info/top_level.txt
trollspeak-1.0.dist-info/RECORD
